{
    "backend": "django",
    "db_name": "",
    "db_pass": "",
    "db_type": "mysql",
    "db_user": "",
    "dbms": "1",
    "description": "generated product",
    "design": "datta-able",
    "docker": "0",
    "err_code": 0,
    "frontend": "",
    "heroku": "0",
    "pattern": "mvc",
    "pro": "0",
    "task_id": "915552af-337e-420c-8f26-b777cde3cedb",
    "task_info": "Upload Sources [0%] - 163 files",
    "task_output": "915552af-337e-420c-8f26-b777cde3cedb.zip",
    "task_result": "SUCCESS",
    "task_state": "RUNNING",
    "task_ts_end": "2024-10-04-03-05-18",
    "task_ts_start": "2024-10-04-03-05-17"
}